Metadata-Version: 2.1
Name: scrapautoscout
Version: 1.3.0
Summary: autoscout24 web scrapper
Home-page: https://github.com/viggleUnik/scrapautoscout
Author: Vicol Cristian
Author-email: vicol.cristianken@gmail.com
License: MIT
Classifier: Development Status :: 1 - Planning
Classifier: Intended Audience :: Developers
Classifier: Programming Language :: Python :: 3
Classifier: Operating System :: Unix
Classifier: Operating System :: MacOS :: MacOS X
Classifier: Operating System :: Microsoft :: Windows
Requires-Python: >=3.6
License-File: LICENSE
